[
  {
    "slug": "the-break-that-broke-the-internet",
    "client": "Burger King",
    "campaign": "The *Break* That Broke the Internet",
    "agency": "David Miami",
    "tagline": "Even legends have favorites",
    "year": "2024",
    "category": "Creativity",
    "imageUrl": "https://image.pollinations.ai/prompt/cinematic%20brand%20activation%20campaign%20photography%2C%20dramatic%20moody%20lighting%2C%20dark%20background%2C%20Burger%20King%20The%20Break%20That%20Broke%20the%20Internet%20Even%20legends%20have%20favorites%2C%20award%20winning%2C%20no%20text%2C%20editorial?width=1200&height=800&seed=3221&nologo=true",
    "publishedAt": "2026-03-17T00:54:39.658Z"
  },
  {
    "slug": "the-great-peel-deal",
    "client": "Ryanair",
    "campaign": "The Great *Peel* Deal",
    "agency": "Tropical Minds London",
    "tagline": "Flights so sweet, they're bananas",
    "year": "2024",
    "category": "Creativity",
    "publishedAt": "2026-03-16T19:35:37.059Z"
  },
  {
    "slug": "cover-your-truth",
    "client": "e.l.f. Cosmetics",
    "campaign": "Cover Your *Truth*",
    "agency": "Midnight & Co.",
    "tagline": "Beauty Beyond Bruises",
    "year": "2024",
    "category": "Creativity",
    "publishedAt": "2026-03-16T14:51:36.178Z"
  }
]